LICENSE.txt
README.md
setup.cfg
setup.py
Topsis_Diksha_102016116/__init__.py
Topsis_Diksha_102016116/topsis102016116.py
Topsis_Diksha_102016116.egg-info/PKG-INFO
Topsis_Diksha_102016116.egg-info/SOURCES.txt
Topsis_Diksha_102016116.egg-info/dependency_links.txt
Topsis_Diksha_102016116.egg-info/requires.txt
Topsis_Diksha_102016116.egg-info/top_level.txt